autotiktokenizer/__init__.py
autotiktokenizer/autotiktokenizer.py
autotiktokenizer-0.2.2.dist-info/LICENSE
autotiktokenizer-0.2.2.dist-info/METADATA
autotiktokenizer-0.2.2.dist-info/WHEEL
autotiktokenizer-0.2.2.dist-info/top_level.txt
autotiktokenizer-0.2.2.dist-info/RECORD
