Metadata-Version: 2.1
Name: autotiktokenizer
Version: 0.2.2
Summary: 🧰 The AutoTokenizer that TikToken always needed -- Load any tokenizer with TikToken now! ✨
Author-email: Bhavnick Minhas <bhavnicksm@gmail.com>
License: MIT License
Project-URL: Homepage, https://github.com/bhavnicksm/autotiktokenizer
Keywords: tokenizer,transformers,huggingface,tiktoken
Classifier: License :: OSI Approved :: MIT License
Classifier: Programming Language :: Python
Classifier: Programming Language :: Python :: 3
Classifier: Programming Language :: Python :: 3.8
Classifier: Programming Language :: Python :: 3.9
Classifier: Programming Language :: Python :: 3.10
Classifier: Programming Language :: Python :: 3.11
Requires-Python: >=3.8
License-File: LICENSE
Requires-Dist: tiktoken>=0.2.0
Requires-Dist: huggingface-hub>=0.0.12
Provides-Extra: dev
Requires-Dist: pytest>=6.2.0; extra == "dev"
